ovos_phal_plugin_mac/__init__.py
ovos_phal_plugin_mac/version.py
ovos_phal_plugin_mac-0.1.0.dist-info/METADATA
ovos_phal_plugin_mac-0.1.0.dist-info/WHEEL
ovos_phal_plugin_mac-0.1.0.dist-info/entry_points.txt
ovos_phal_plugin_mac-0.1.0.dist-info/top_level.txt
ovos_phal_plugin_mac-0.1.0.dist-info/RECORD
