Metadata-Version: 2.1
Name: ovos-phal-plugin-mac
Version: 0.1.0
Summary: # PHAL-plugin-mac
Author-email: Mike Gray <mike@oscillatelabs.net>
License: Apache-2.0
Project-URL: Homepage, https://github.com/OscillateLabsLLC/ovos-phal-plugin-mac
Project-URL: Repository, https://github.com/OscillateLabsLLC/ovos-phal-plugin-mac
Keywords: ovos,plugin,voice,assistant
Requires-Python: >=3.9
Requires-Dist: ovos-utils
Requires-Dist: ovos-bus-client
Requires-Dist: ovos-workshop
Requires-Dist: ovos-plugin-manager
Requires-Dist: osascript==2020.12.3
Provides-Extra: test
Requires-Dist: pytest; extra == "test"
Requires-Dist: pytest-cov; extra == "test"
